__init__.py
sestat/SecondaryStructure.py
sestat/Structure.py
sestat/__init__.py
sestat-1.0.2.dist-info/METADATA
sestat-1.0.2.dist-info/WHEEL
sestat-1.0.2.dist-info/top_level.txt
sestat-1.0.2.dist-info/RECORD
