Metadata-Version: 2.1
Name: sestat
Version: 1.0.2
Summary: Secondary Structure analysis tool for building and processing.
Author-email: Dainius Kirsnauskas <dainius@genomika.lt>
Requires-Python: >=3.8
